db_handy/__init__.py
db_handy/database.py
db_handy/log.py
db_handy/qdrant.py
db_handy/rds.py
db_handy/rq.py
db_handy/sql.py
db_handy/server/mcp/__init__.py
db_handy/server/mcp/content.py
db_handy/server/mcp/math.py
db_handy/server/mcp/resource.py
db_handy/server/mcp/weather.py
db_handy/server/routers/__init__.py
db_handy/server/routers/admin.py
db_handy/server/routers/user.py
db_handy-0.2.3.dist-info/METADATA
db_handy-0.2.3.dist-info/WHEEL
db_handy-0.2.3.dist-info/top_level.txt
db_handy-0.2.3.dist-info/RECORD
