Metadata-Version: 2.4
Name: db-handy
Version: 0.2.3
Summary: Add your description here
Requires-Python: >=3.12
Requires-Dist: anyio>=4.11.0
Requires-Dist: dotenv>=0.9.9
Requires-Dist: fastapi>=0.119.1
Requires-Dist: pytest>=8.4.2
Requires-Dist: pytest-asyncio>=1.2.0
Requires-Dist: pytest-tornasync>=0.6.0.post2
Requires-Dist: qdrant-client>=1.15.1
Requires-Dist: redis>=7.0.0
Requires-Dist: sqlalchemy>=2.0.44
Requires-Dist: toml>=0.10.2
Requires-Dist: utils-tool==0.1.3
Requires-Dist: uvicorn>=0.38.0
